Timetrap_Youtrack-0.1.data/scripts/timetrap_youtrack
timetrap_youtrack_package/__init__.py
Timetrap_Youtrack-0.1.dist-info/METADATA
Timetrap_Youtrack-0.1.dist-info/WHEEL
Timetrap_Youtrack-0.1.dist-info/top_level.txt
Timetrap_Youtrack-0.1.dist-info/RECORD
